op_log-0.22.1.dist-info/licenses/LICENSE
oplog/__init__.py
oplog/constants.py
oplog/exceptions.py
oplog/operated.py
oplog/operation.py
oplog/operation_handler.py
oplog/operation_log_filter.py
oplog/operation_step.py
oplog/formatters/__init__.py
oplog/formatters/base_operation_formatter.py
oplog/formatters/csv_operation_formatter.py
oplog/formatters/verbose_operation_formatter.py
oplog/tests/__init__.py
oplog/tests/logged_test_case.py
oplog/tests/test_operated.py
oplog/tests/test_operated_async.py
oplog/tests/test_operation.py
oplog/tests/test_operation_handler.py
oplog/tests/test_operation_log_filter.py
oplog/tests/formatters/__init__.py
oplog/tests/formatters/test_base_operation_formatter.py
oplog/tests/formatters/test_csv_operation_formatter.py
oplog/tests/formatters/test_verbose_operation_formatter.py
op_log-0.22.1.dist-info/METADATA
op_log-0.22.1.dist-info/WHEEL
op_log-0.22.1.dist-info/top_level.txt
op_log-0.22.1.dist-info/RECORD
