Metadata-Version: 2.4
Name: op-log
Version: 0.22.1
Summary: Easy-to-use context-rich Python logging library.
Author-email: Ori Bar-ilan <python.oplog@gmail.com>
License: MIT License
Project-URL: Homepage, https://github.com/oribarilan/oplog
Keywords: oplog,logging,logger
Classifier: License :: OSI Approved :: MIT License
Classifier: Programming Language :: Python
Classifier: Programming Language :: Python :: 3
Requires-Python: >=3.9
License-File: LICENSE
Provides-Extra: dev
Requires-Dist: pip-tools; extra == "dev"
Requires-Dist: pytest; extra == "dev"
Dynamic: license-file
